tainlp/__init__.py
TaiNLP-0.0.1.dev0.dist-info/METADATA
TaiNLP-0.0.1.dev0.dist-info/WHEEL
TaiNLP-0.0.1.dev0.dist-info/top_level.txt
TaiNLP-0.0.1.dev0.dist-info/RECORD
